[
  {
    "id": "5",
    "name": "GLOWING COLLAR PENDANT",
    "price": "$29.99",
    "description1": "Does your dog run off during his night potty trip? Or maybe your nighttime walk takes you past roads without street lights.",
    "description2": "If you are having pooch visibility problems, then this Glowing Collar Pendant is exactly what you need. This light-up pendant allows you to keep track of your dog in the dark, fog and snow. This small LED light clips onto your dog’s collar, providing instant light. Once you are done, unclip it, and throw it in your junk drawer until next time!",
    "image": [
      "https://thetinypaws.com/cdn/shop/products/product-image-799317625_720x.jpg?v=1643869766",
      "https://thetinypaws.com/cdn/shop/products/product-image-1913238525_150x.jpg?v=1643869763",
      "https://thetinypaws.com/cdn/shop/products/product-image-799317628_150x.jpg?v=1643869762"
    ],
    "description img": "https://cdn.shopify.com/s/files/1/0605/0480/1480/files/Screenshot_35_480x480.png?v=1645365690",
    "category": "Leash & Harness",
    "rating": 4.5,
    "Size": ["Blue", "Green", "Pink", "Yellow"]
  },
  {
    "id": "5",
    "name": "BUNGEE SEAT-BELT LEASH",
    "price": "$36.99",
    "description1": "PROTECT YOUR PRECIOUS PUP FROM INJURIES!",
    "description2": "Our furry friends love to move around in the car a lot but this can often result in risk of accident & injury to your precious pup. Why not keep him in place with our dog seat belt leash? This is a secure telescopic bungee dog seat belt leash so that you can have a safe ride with your pup & peace of mind. It's really comfortable & protects your pup from falling or hurting itself while moving in the car too much. Our dog seat belt leash feature unique, durable fabric, quality hardware, and a strong nylon core. They're machine washable and made to last:",
    "image": [
      "https://thetinypaws.com/cdn/shop/products/product-image-1937744081_150x.jpg?v=1645335923",
      "https://thetinypaws.com/cdn/shop/products/product-image-1937744079_150x.jpg?v=1645335923",
      "https://thetinypaws.com/cdn/shop/products/product-image-1937744101_300x300.jpg?v=1645335923"
    ],
    "description img": "https://cdn.shopify.com/s/files/1/0513/2638/6369/f…d9c4a32a6d30f4b516745235_480x480.jpg?v=1608476607",
    "category": "Leash & Harness",
    "rating": 5,
    "Size": ["Blue", "Black", "Red", "Gray"]
  },
  {
    "id": "5",
    "name": "MULTIFUNCTIONAL DOG LEASH 2.0",
    "price": "$59.99",
    "description1": "THIS PRODUCT IS A LIFE-SAVER, IF YOU TAKE YOUR DOG TO WALKS, HIKES, OR RUNS! ",
    "description2": "The All-New Multifunctional Leash is a must-have for all dog owners! It includes everything that you could ever need!",
    "image": [
      "https://thetinypaws.com/cdn/shop/products/blueeeeeee_150x.webp?v=1663784324",
      "https://thetinypaws.com/cdn/shop/products/481A3DD07E09F2D77F1010F9F3410958_150x.jpg?v=1663784324",
      "https://thetinypaws.com/cdn/shop/products/4A646FF302A90E44471E72726497B328_150x.jpg?v=1663784324"
    ],
    "description img": "https://cdn.shopify.com/s/files/1/0605/0480/1480/files/Screenshot_2022-09-21_at_12.36.23_PM_480x480.png?v=1663744775",
    "category": "Leash & Harness",
    "rating": 4.5,
    "Size": ["Black", "Blue", "Red"]
  },
  {
    "id": "5",
    "name": "PET ADJUSTABLE WALKING LEASH",
    "price": "$36.99",
    "description1": "FEATURES",
    "description2": "All cat lovers know that cats are very sensitive. Before a cat get used to its harness, it will keep backing off to get rid of the harness. To solve this problem completely, our designer develop this adjustable collar harness. You can tie or loose the collar to fit your cat's neck circumference so that your lovely cat will never escape the harness again.",
    "image": [
      "https://thetinypaws.com/cdn/shop/products/product-image-1886848482_150x.jpg?v=1641534244",
      "https://thetinypaws.com/cdn/shop/products/product-image-1815669684_150x.jpg?v=1641534247",
      "https://thetinypaws.com/cdn/shop/products/product-image-1815669680_150x.jpg?v=1641534259"
    ],
    "description img": "https://cdn.shopify.com/s/files/1/0605/0480/1480/f…022-04-28_at_12.52.47_AM_600x600.png?v=1651087402",
    "category": "Leash & Harness",
    "rating": 3.5,
    "Size": ["Black", "Blue", "Red", "pink"]
  },
  {
    "id": "5",
    "name": "ADJUSTABLE CAR SEAT HARNESS",
    "price": "$33.99",
    "description1": "PREMIUM QUALITY",
    "description2": "Made of high quality nylon fabric, with metal swivel snap and buckle. Keeps your pet safely restrained and secured in vehicle while driving. ADJUSTABLE: The length of seat belt can be adjusted from 16 to 27 inch, which allows your dog to sit, stand or lie down comfortably in your car.",
    "image": ["https://thetinypaws.com/cdn/shop/products/S38e290294ee9492eb5fe5a36946f1884X_150x.jpg?v=1669034338","https://thetinypaws.com/cdn/shop/products/S5a2f698ab1204c92a18ef9b948ddfccfZ_150x.jpg?v=1669034338","https://thetinypaws.com/cdn/shop/products/Sdf1770f6df764dde955ed10ce9748d0ah_150x.jpg?v=1669034338"],
    "description img": "https://cdn.shopify.com/s/files/1/0605/0480/1480/f…product-image-1899181699_480x480.jpg?v=1649745202",
    "category": "Leash & Harness",
    "rating": 4.5,
    "Size": ["Black", "Blue", "Red", "pink"]
  },
  {
    "id": "5",
    "name": "METAL NECK CHAIN",
    "price": "$39.99",
    "description1": "SPECIFICATIONS",
    "description2": "Pattern: Solid, Feature:Personalized , Color: Gold, Silver , Collar Type: Basic Collars , Item Size:37cm*2cm",
    "image": ["https://thetinypaws.com/cdn/shop/products/Saf42575…5c14d4e9f0a767861bde50en_300x300.jpg?v=1657249200","https://thetinypaws.com/cdn/shop/products/S1e3de71370bc4a7d94b6f0ac2f2352024_150x.jpg?v=1657249202","https://thetinypaws.com/cdn/shop/products/H9492ae9fbbef4e14ad98cc7658d32fe62_150x.jpg?v=1657249214"],
    "description img": "https://thetinypaws.com/cdn/shop/products/H9492ae9fbbef4e14ad98cc7658d32fe62_150x.jpg?v=1657249214",
    "category": "Leash & Harness",
    "rating": 4.5,
    "Size": ["Silver", "Black", "Gold"]
  }
]
